flake8_author.py
flake8_author-2.2.0.dist-info/licenses/LICENSE
flake8_author-2.2.0.dist-info/METADATA
flake8_author-2.2.0.dist-info/WHEEL
flake8_author-2.2.0.dist-info/entry_points.txt
flake8_author-2.2.0.dist-info/top_level.txt
flake8_author-2.2.0.dist-info/RECORD
