Metadata-Version: 2.4
Name: flake8-author
Version: 2.2.0
Summary: Flake8 __author__ checker
Author-email: Jon Parise <jon@indelible.org>
License-Expression: MIT
Project-URL: Homepage, https://github.com/jparise/flake8-author
Project-URL: Repository, https://github.com/jparise/flake8-author
Project-URL: Issues, https://github.com/jparise/flake8-author/issues
Project-URL: Changelog, https://github.com/jparise/flake8-author/blob/main/CHANGELOG.rst
Keywords: flake8,__author__
Classifier: Development Status :: 5 - Production/Stable
Classifier: Environment :: Console
Classifier: Framework :: Flake8
Classifier: Intended Audience :: Developers
Classifier: Programming Language :: Python
Classifier: Programming Language :: Python :: 3 :: Only
Classifier: Programming Language :: Python :: 3.9
Classifier: Programming Language :: Python :: 3.10
Classifier: Programming Language :: Python :: 3.11
Classifier: Programming Language :: Python :: 3.12
Classifier: Programming Language :: Python :: 3.13
Classifier: Topic :: Software Development :: Libraries :: Python Modules
Classifier: Topic :: Software Development :: Quality Assurance
Requires-Python: >=3.9
License-File: LICENSE
Requires-Dist: flake8>=3.0.0
Dynamic: license-file
